README.txt
ZopePublicLicense.txt
bootstrap.py
buildout.cfg
setup.py
src/zc/__init__.py
src/zc.shortcut.egg-info/PKG-INFO
src/zc.shortcut.egg-info/SOURCES.txt
src/zc.shortcut.egg-info/dependency_links.txt
src/zc.shortcut.egg-info/namespace_packages.txt
src/zc.shortcut.egg-info/not-zip-safe
src/zc.shortcut.egg-info/requires.txt
src/zc.shortcut.egg-info/top_level.txt
src/zc/shortcut/TODO.txt
src/zc/shortcut/__init__.py
src/zc/shortcut/adapters.py
src/zc/shortcut/adapters.txt
src/zc/shortcut/adding.py
src/zc/shortcut/adding.txt
src/zc/shortcut/configure.zcml
src/zc/shortcut/constraints.py
src/zc/shortcut/factory.py
src/zc/shortcut/factory.txt
src/zc/shortcut/i18n.py
src/zc/shortcut/interfaces.py
src/zc/shortcut/proxy.py
src/zc/shortcut/proxy.txt
src/zc/shortcut/shortcut.py
src/zc/shortcut/shortcut.txt
src/zc/shortcut/subscribers.py
src/zc/shortcut/tests.py
