Metadata-Version: 1.0
Name: zc.shortcut
Version: 1.0
Summary: Symlinks for Zope 3.
